lauterbach/trace32/rcl/__init__.py
lauterbach/trace32/rcl/__version__.py
lauterbach/trace32/rcl/rcl.py
lauterbach/trace32/rcl/_rc/__init__.py
lauterbach/trace32/rcl/_rc/_address.py
lauterbach/trace32/rcl/_rc/_breakpoint.py
lauterbach/trace32/rcl/_rc/_command.py
lauterbach/trace32/rcl/_rc/_directaccess.py
lauterbach/trace32/rcl/_rc/_error.py
lauterbach/trace32/rcl/_rc/_functions.py
lauterbach/trace32/rcl/_rc/_library.py
lauterbach/trace32/rcl/_rc/_memory.py
lauterbach/trace32/rcl/_rc/_memory_bundle.py
lauterbach/trace32/rcl/_rc/_memory_exceptions.py
lauterbach/trace32/rcl/_rc/_practice.py
lauterbach/trace32/rcl/_rc/_register.py
lauterbach/trace32/rcl/_rc/_symbol.py
lauterbach/trace32/rcl/_rc/_variable.py
lauterbach/trace32/rcl/_rc/common.py
lauterbach/trace32/rcl/_rc/hlinknet.py
lauterbach_trace32_rcl-1.1.5.dist-info/licenses/LICENSE
lauterbach_trace32_rcl-1.1.5.dist-info/METADATA
lauterbach_trace32_rcl-1.1.5.dist-info/WHEEL
lauterbach_trace32_rcl-1.1.5.dist-info/top_level.txt
lauterbach_trace32_rcl-1.1.5.dist-info/RECORD
