Metadata-Version: 2.4
Name: lauterbach-trace32-rcl
Version: 1.1.5
Summary: Lauterbach TRACE32 Python Remote Control Library
Home-page: https://www.lauterbach.com
Author: Lauterbach GmbH
Author-email: support@lauterbach.com
Maintainer: Lauterbach GmbH
Maintainer-email: support@lauterbach.com
License: MIT
Project-URL: Documentation, https://pyrcl.readthedocs.io
Project-URL: Repository, https://gitlab.com/lauterbach/pyrcl
Classifier: Programming Language :: Python :: 3
Classifier: Programming Language :: Python :: 3.9
Classifier: License :: OSI Approved :: MIT License
Classifier: Operating System :: OS Independent
Classifier: Topic :: Software Development :: Debuggers
Classifier: Intended Audience :: Developers
License-File: LICENSE
Dynamic: license-file
